py2winapp/__init__.py
py2winapp/downloader.py
py2winapp/generate_exe.py
py2winapp/genexe_template
py2winapp/py2winapp.py
py2winapp-0.1.0.dist-info/LICENSE
py2winapp-0.1.0.dist-info/METADATA
py2winapp-0.1.0.dist-info/WHEEL
py2winapp-0.1.0.dist-info/RECORD
