Metadata-Version: 2.1
Name: py2winapp
Version: 0.1.0
Summary: Make runnable apps from your python scripts!
License: MIT
Author: Ruslan Iskov
Author-email: ruslan.rv.ua@gmail.com
Requires-Python: >=3.10,<4.0
Classifier: License :: OSI Approved :: MIT License
Classifier: Programming Language :: Python :: 3
Classifier: Programming Language :: Python :: 3.10
Classifier: Programming Language :: Python :: 3.11
Requires-Dist: loguru (>=0.7.0,<0.8.0)
Requires-Dist: pip-requirements-parser (>=32.0.1,<33.0.0)
Requires-Dist: python-slugify (>=8.0.1,<9.0.0)
Requires-Dist: pywin32 (>=306,<307)
Requires-Dist: requests (>=2.31.0,<3.0.0)
